{
  "project_info": {
    "project_number": "274090461017",
    "project_id": "online-doctor-18a73",
    "storage_bucket": "online-doctor-18a73.appspot.com"
  },
  "client": [
    {
      "client_info": {
        "mobilesdk_app_id": "1:274090461017:android:612b2128483d63f8a8ae48",
        "android_client_info": {
          "package_name": "com.verbosetech.doctoworld_seller"
        }
      },
      "oauth_client": [
        {
          "client_id": "274090461017-llsm2rkam4qvlvoi02tbk382qb3qqo88.apps.googleusercontent.com",
          "client_type": 1,
          "android_info": {
            "package_name": "com.verbosetech.doctoworld_seller",
            "certificate_hash": "559cff3be6c4e3db9572adcb66332a9ac7e4d296"
          }
        },
        {
          "client_id": "274090461017-4b12230nt9f8r191pnr2gachcjknbf2r.apps.googleusercontent.com",
          "client_type": 3
        }
      ],
      "api_key": [
        {
          "current_key": "AIzaSyC93hnUvYNFw4X4TReS3KTgLFUcRpIQRpg"
        }
      ],
      "services": {
        "appinvite_service": {
          "other_platform_oauth_client": [
            {
              "client_id": "274090461017-4b12230nt9f8r191pnr2gachcjknbf2r.apps.googleusercontent.com",
              "client_type": 3
            }
          ]
        }
      }
    },
    {
      "client_info": {
        "mobilesdk_app_id": "1:274090461017:android:80df58cec9f9e32ba8ae48",
        "android_client_info": {
          "package_name": "com.verbosetech.doctoworld_user"
        }
      },
      "oauth_client": [
        {
          "client_id": "274090461017-kcgpjbbkajl98csof7h7g28fiiku87gi.apps.googleusercontent.com",
          "client_type": 1,
          "android_info": {
            "package_name": "com.verbosetech.doctoworld_user",
            "certificate_hash": "02a9eb4f1b7920d0cd7203d261d51e958e7988c4"
          }
        },
        {
          "client_id": "274090461017-4b12230nt9f8r191pnr2gachcjknbf2r.apps.googleusercontent.com",
          "client_type": 3
        }
      ],
      "api_key": [
        {
          "current_key": "AIzaSyC93hnUvYNFw4X4TReS3KTgLFUcRpIQRpg"
        }
      ],
      "services": {
        "appinvite_service": {
          "other_platform_oauth_client": [
            {
              "client_id": "274090461017-4b12230nt9f8r191pnr2gachcjknbf2r.apps.googleusercontent.com",
              "client_type": 3
            }
          ]
        }
      }
    },
    {
      "client_info": {
        "mobilesdk_app_id": "1:274090461017:android:cfd94d6fbff239a9a8ae48",
        "android_client_info": {
          "package_name": "pk.online_doctor.doctor"
        }
      },
      "oauth_client": [
        {
          "client_id": "274090461017-4b12230nt9f8r191pnr2gachcjknbf2r.apps.googleusercontent.com",
          "client_type": 3
        }
      ],
      "api_key": [
        {
          "current_key": "AIzaSyC93hnUvYNFw4X4TReS3KTgLFUcRpIQRpg"
        }
      ],
      "services": {
        "appinvite_service": {
          "other_platform_oauth_client": [
            {
              "client_id": "274090461017-4b12230nt9f8r191pnr2gachcjknbf2r.apps.googleusercontent.com",
              "client_type": 3
            }
          ]
        }
      }
    }
  ],
  "configuration_version": "1"
}